bandripper/__init__.py
bandripper/bandripper.py
bandripper/py.typed
bandripper/request.py
bandripper-0.3.1.dist-info/METADATA
bandripper-0.3.1.dist-info/WHEEL
bandripper-0.3.1.dist-info/entry_points.txt
bandripper-0.3.1.dist-info/licenses/LICENSE.txt
bandripper-0.3.1.dist-info/RECORD
