Metadata-Version: 2.4
Name: bandripper
Version: 0.3.1
Summary: Rip mp3s from bandcamp.
Project-URL: Homepage, https://github.com/matt-manes/bandripper
Project-URL: Documentation, https://github.com/matt-manes/bandripper/tree/main/docs
Project-URL: Source code, https://github.com/matt-manes/bandripper/tree/main/src/bandripper
Author-email: Matt Manes <mattmanes@pm.me>
License-File: LICENSE.txt
Keywords: audio,bandcamp,download,downloader,music
Classifier: License :: OSI Approved :: MIT License
Classifier: Operating System :: OS Independent
Classifier: Programming Language :: Python :: 3
Requires-Python: <3.12,>=3.10
Requires-Dist: argshell
Requires-Dist: beautifulsoup4
Requires-Dist: gruel
Requires-Dist: noiftimer
Requires-Dist: pathier
Requires-Dist: printbuddies
Requires-Dist: quickpool
Requires-Dist: requests
Requires-Dist: rich
Requires-Dist: typing-extensions
Requires-Dist: urllib3
